poetry_plugin_install_all/__init__.py
poetry_plugin_install_all/command.py
poetry_plugin_install_all/plugins.py
poetry_plugin_install_all-1.0.0.dist-info/METADATA
poetry_plugin_install_all-1.0.0.dist-info/WHEEL
poetry_plugin_install_all-1.0.0.dist-info/entry_points.txt
poetry_plugin_install_all-1.0.0.dist-info/RECORD
